phagetrix/__init__.py
phagetrix/api.py
phagetrix/cli.py
phagetrix/constants.py
phagetrix/core.py
phagetrix/output.py
phagetrix/parser.py
phagetrix-1.0.6.dist-info/METADATA
phagetrix-1.0.6.dist-info/WHEEL
phagetrix-1.0.6.dist-info/entry_points.txt
phagetrix-1.0.6.dist-info/licenses/LICENSE
phagetrix-1.0.6.dist-info/RECORD
