Metadata-Version: 2.4
Name: phagetrix
Version: 1.0.6
Summary: Optimizer for degenerate codon use in phage library generation
License-Expression: GPL-3.0-or-later
License-File: LICENSE
Keywords: bioinformatics,phage-display,codon-optimization,molecular-biology,protein-engineering,synthetic-biology,directed-evolution,dna-synthesis,degenerate-codons,library-design
Author: Reto Stamm
Author-email: reto@retospect.ch
Requires-Python: >=3.10
Classifier: Development Status :: 5 - Production/Stable
Classifier: Intended Audience :: Science/Research
Classifier: Operating System :: OS Independent
Classifier: Programming Language :: Python :: 3
Classifier: Programming Language :: Python :: 3.10
Classifier: Programming Language :: Python :: 3.11
Classifier: Programming Language :: Python :: 3.12
Classifier: Programming Language :: Python :: 3.13
Classifier: Topic :: Scientific/Engineering :: Bio-Informatics
Classifier: Topic :: Software Development :: Libraries :: Python Modules
Requires-Dist: python-codon-tables (>=0.1.12)
Requires-Dist: quantiphy (>=2.19)
Project-URL: Bug Tracker, https://github.com/retospect/phagetrix/issues
Project-URL: Documentation, https://github.com/retospect/phagetrix
Project-URL: Homepage, https://github.com/retospect/phagetrix
Project-URL: Repository, https://github.com/retospect/phagetrix
